pyeurostat/__init__.py
pyeurostat/explorer.py
pyeurostat/sdmx_client.py
pyeurostat-1.0.0.dist-info/licenses/LICENSE
pyeurostat-1.0.0.dist-info/METADATA
pyeurostat-1.0.0.dist-info/WHEEL
pyeurostat-1.0.0.dist-info/top_level.txt
pyeurostat-1.0.0.dist-info/RECORD
