Metadata-Version: 2.4
Name: pyeurostat
Version: 1.0.0
Summary: Modern Python client for EuroStat data using SDMX API
Author-email: onerafaz <onerafaz@gmail.com>
License: MIT
Project-URL: Homepage, https://github.com/Onerafaz/pyeurostat
Project-URL: Repository, https://github.com/Onerafaz/pyeurostat
Project-URL: Documentation, https://github.com/Onerafaz/pyeurostat#readme
Project-URL: Bug Tracker, https://github.com/Onerafaz/pyeurostat/issues
Keywords: eurostat,statistics,data,europe,api,sdmx,eurostat-api,economic-data
Classifier: Development Status :: 4 - Beta
Classifier: Intended Audience :: Developers
Classifier: Intended Audience :: Science/Research
Classifier: License :: OSI Approved :: MIT License
Classifier: Programming Language :: Python :: 3
Classifier: Programming Language :: Python :: 3.8
Classifier: Programming Language :: Python :: 3.9
Classifier: Programming Language :: Python :: 3.10
Classifier: Programming Language :: Python :: 3.11
Classifier: Programming Language :: Python :: 3.12
Classifier: Topic :: Scientific/Engineering
Classifier: Topic :: Scientific/Engineering :: Information Analysis
Requires-Python: >=3.8
License-File: LICENSE
Requires-Dist: pandas>=1.3.0
Requires-Dist: plotly>=5.0.0
Requires-Dist: requests>=2.25.0
Provides-Extra: dev
Requires-Dist: pytest>=7.0; extra == "dev"
Requires-Dist: black>=22.0; extra == "dev"
Requires-Dist: flake8>=4.0; extra == "dev"
Dynamic: license-file
